{"nodes":{"node:1":{"location":{"x":-42,"y":14}},"node:13":{"location":{"x":1290,"y":222}},"node:18":{"location":{"x":2410,"y":222}},"node:23":{"location":{"x":-58,"y":414}},"node:25":{"location":{"x":-58,"y":590}},"node:27":{"location":{"x":-58,"y":766}},"node:29":{"location":{"x":-58,"y":926}},"node:3":{"location":{"x":296,"y":222}},"node:31":{"location":{"x":1352,"y":926}},"node:36":{"location":{"x":1832,"y":418}},"node:41":{"location":{"x":-58,"y":1150}},"node:43":{"location":{"x":2456,"y":1134}},"node:48":{"location":{"x":3192,"y":1134}},"node:53":{"location":{"x":3192,"y":578}},"node:58":{"location":{"x":728,"y":766}},"node:8":{"location":{"x":794,"y":222}}},"selection":null,"view":{"scroll":{"x":-50.3644256591796875,"y":-77.6417694091796875},"zoom":0.749999940395355225}}